[
	{
		"date": "2020-05-06T14:53:06.766+0000",
		"retailer": 2,
		"cust": 1,
		"book": 6,
		"amnt": 10,
		"cost": 12500
	},
	{
		"date": "2020-05-06T13:23:15.533+0000",
		"retailer": 1,
		"cust": 5,
		"book": 3,
		"amnt": 1,
		"cost": 2340
	},
	{
		"date": "2020-05-06T12:44:33.766+0000",
		"retailer": 1,
		"cust": 5,
		"book": 4,
		"amnt": 2,
		"cost": 8000
	},
	{
		"date": "2020-05-06T11:52:24.726+0000",
		"retailer": 3,
		"cust": 1,
		"book": 2,
		"amnt": 1,
		"cost": 1500
	},
	{
		"date": "2020-05-07T12:10:06.766+0000",
		"retailer": 2,
		"cust": 4,
		"book": 3,
		"amnt": 5,
		"cost": 11700
	},
	{
		"date": "2020-05-07T12:15:45.766+0000",
		"retailer": 2,
		"cust": 4,
		"book": 5,
		"amnt": 4,
		"cost": 4000
	},
	{
		"date": "2020-05-07T18:10:22.766+0000",
		"retailer": 1,
		"cust": 3,
		"book": 2,
		"amnt": 10,
		"cost": 15000
	},
	{
		"date": "2020-05-04T12:10:06.766+0000",
		"retailer": 3,
		"cust": 1,
		"book": 2,
		"amnt": 1,
		"cost": 1500
	},
	{
		"date": "2020-05-04T17:22:45.766+0000",
		"retailer": 3,
		"cust": 1,
		"book": 5,
		"amnt": 1,
		"cost": 1000
	},
	{
		"date": "2020-05-04T11:14:07.766+0000",
		"retailer": 2,
		"cust": 5,
		"book": 6,
		"amnt": 10,
		"cost": 12500
	}
]
